setup.py
gmail/__init__.py
gmail/exceptions.py
gmail/gmail.py
gmail/mailbox.py
gmail/message.py
gmail/utf.py
gmail/utils.py
pygmail.egg-info/PKG-INFO
pygmail.egg-info/SOURCES.txt
pygmail.egg-info/dependency_links.txt
pygmail.egg-info/top_level.txt