Metadata-Version: 1.1
Name: pygmail
Version: 0.0.5.4
Summary: A Pythonic interface for Google Mail.
Home-page: https://github.com/charlierguo/gmail
Author: Charlie Guo
Author-email: FIXME
License: MIT
Keywords: google gmail
Platform: UNKNOWN
Classifier: Development Status :: 3 - Alpha
Classifier: Topic :: Communications :: Email
Classifier: License :: OSI Approved :: MIT License
